waanverse_mailer/__init__.py
waanverse_mailer/apps.py
waanverse_mailer/email_service.py
waanverse_mailer/utils.py
waanverse_mailer/version.py
waanverse_mailer/config/__init__.py
waanverse_mailer/config/schema.py
waanverse_mailer/config/settings.py
waanverse_mailer-0.0.4.dist-info/LICENSE
waanverse_mailer-0.0.4.dist-info/METADATA
waanverse_mailer-0.0.4.dist-info/WHEEL
waanverse_mailer-0.0.4.dist-info/top_level.txt
waanverse_mailer-0.0.4.dist-info/RECORD
